xml_etree_from_tree_sitter/__init__.py
xml_etree_from_tree_sitter/internal.py
xml_etree_from_tree_sitter/py.typed
xml_etree_from_tree_sitter-0.1.0.dist-info/METADATA
xml_etree_from_tree_sitter-0.1.0.dist-info/WHEEL
xml_etree_from_tree_sitter-0.1.0.dist-info/licenses/LICENSE
xml_etree_from_tree_sitter-0.1.0.dist-info/RECORD
